<?xml version="1.0" encoding="UTF-8"?>
<feature id="com.jboss.devstudio.integration-stack.bpr.feature" label="%featureName" version="8.0.0.qualifier" provider-name="%providerName" plugin="com.jboss.devstudio.integration-stack">
  <description url="https://access.redhat.com/documentation/en-US/Red_Hat_JBoss_Developer_Studio/">%description</description>
  <copyright>%copyright</copyright>
  <license url="%licenseURL">%license</license>

  <requires>
    <import feature="org.eclipse.help"/>
    <import feature="org.eclipse.jdt"/>
    <import feature="org.eclipse.jgit"/>
    <import feature="org.eclipse.egit"/>
    <import feature="org.eclipse.rse"/>
    <import feature="org.eclipse.tm.terminal"/>
    <!-- <import plugin="" /> -->

    <import plugin="com.jboss.devstudio.core.project.examples"/>
    <import plugin="com.jboss.devstudio.core.usage.branding"/>
    <import plugin="com.jboss.devstudio.core.central"/>
    <import feature="org.jboss.tools.central.feature"/> 
    <import feature="org.jboss.tools.project.examples.feature"/> 
    <import feature="org.jboss.tools.usage.feature"/>

    <import feature="org.jboss.tools.bpel.feature"/>
    <import feature="org.eclipse.bpmn2"/>
    <import feature="org.eclipse.bpmn2.modeler"/>
    <import feature="org.eclipse.bpmn2.modeler.runtime.jboss"/>
    <import feature="org.drools.eclipse.feature"/>
    <import feature="org.guvnor.tools.feature"/>
    <import feature="org.jbpm.eclipse.feature"/>
    <import feature="org.jboss.tools.runtime.drools.detector.feature"/>
    <import feature="org.jboss.tools.runtime.jbpm.detector.feature"/>
  </requires>
</feature>
